gitlab_ml/__init__.py
gitlab_ml/api/client.py
gitlab_ml/api/models.py
gitlab_ml/cli.py
gitlab_ml/commands/auth.py
gitlab_ml/commands/models.py
gitlab_ml/config.py
gitlab_ml/utils/logger.py
gitlab_ml/utils/version.py
gitlab_ml-0.5.0.dist-info/AUTHORS
gitlab_ml-0.5.0.dist-info/LICENSE
gitlab_ml-0.5.0.dist-info/METADATA
gitlab_ml-0.5.0.dist-info/WHEEL
gitlab_ml-0.5.0.dist-info/entry_points.txt
gitlab_ml-0.5.0.dist-info/RECORD
