Metadata-Version: 2.3
Name: gitlab-ml
Version: 0.5.0
Summary: CLI tool for managing machine learning models in GitLab's Model Registry
License: MIT
Author: Ahmet Öner
Requires-Python: >=3.9,<4.0
Classifier: License :: OSI Approved :: MIT License
Classifier: Programming Language :: Python :: 3
Classifier: Programming Language :: Python :: 3.9
Classifier: Programming Language :: Python :: 3.10
Classifier: Programming Language :: Python :: 3.11
Classifier: Programming Language :: Python :: 3.12
Classifier: Programming Language :: Python :: 3.13
Classifier: Topic :: Scientific/Engineering :: Artificial Intelligence
Classifier: Topic :: Software Development :: Build Tools
Classifier: Topic :: Software Development :: Libraries :: Python Modules
Classifier: Topic :: Software Development :: Version Control
Requires-Dist: httpx (>=0.28.1)
Requires-Dist: mlflow-skinny (>=2.20.3)
Requires-Dist: pydantic (>=2.10.6)
Requires-Dist: pydantic-settings (>=2.8.1)
Requires-Dist: python-dateutil (>=2.9.0.post0)
Requires-Dist: python-gitlab (>=5.6.0)
Requires-Dist: rich (>=13.9.4)
Requires-Dist: semver (>=3.0.4)
Requires-Dist: typer[all] (>=0.15.2)
Project-URL: Changelog, https://github.com/ahmetoner/gitlab-ml/blob/main/CHANGELOG.md
Project-URL: Repository, https://github.com/ahmetoner/gitlab-ml
